API_documentation.md
rpsa_client/__init__.py
rpsa_client/client.py
rpsa_client/exceptions.py
rpsa_client/models.py
rpsa_client-0.1.1.dist-info/LICENCE
rpsa_client-0.1.1.dist-info/METADATA
rpsa_client-0.1.1.dist-info/WHEEL
rpsa_client-0.1.1.dist-info/RECORD
