Metadata-Version: 2.1
Name: rpsa-client
Version: 0.1.1
Summary: Python client library for the Rock, Paper, Code! app public API
Home-page: https://github.com/you/rpsa-client
License: MIT
Keywords: rpsa,api,client,httpx,pydantic
Author: Adrian Bohner
Author-email: adrian.bohner@onespire.hu
Requires-Python: >=3.9,<4.0
Classifier: Development Status :: 4 - Beta
Classifier: Intended Audience :: Developers
Classifier: License :: OSI Approved :: MIT License
Classifier: Programming Language :: Python :: 3
Classifier: Programming Language :: Python :: 3.9
Classifier: Programming Language :: Python :: 3.10
Classifier: Programming Language :: Python :: 3.11
Classifier: Programming Language :: Python :: 3.12
Classifier: Topic :: Internet :: WWW/HTTP
Classifier: Topic :: Software Development :: Libraries
Requires-Dist: httpx (>=0.24.1,<0.25.0)
Requires-Dist: pydantic (>=2.0,<3.0)
Project-URL: Documentation, https://github.com/you/rpsa-client#readme
Project-URL: Repository, https://github.com/you/rpsa-client
